README.md
main.py
setup.py
CLI_Excel_Productive_tool.egg-info/PKG-INFO
CLI_Excel_Productive_tool.egg-info/SOURCES.txt
CLI_Excel_Productive_tool.egg-info/dependency_links.txt
CLI_Excel_Productive_tool.egg-info/entry_points.txt
CLI_Excel_Productive_tool.egg-info/requires.txt
CLI_Excel_Productive_tool.egg-info/top_level.txt